env_canada/10x20.pbm
env_canada/10x20.pil
env_canada/__init__.py
env_canada/constants.py
env_canada/ec_aqhi.py
env_canada/ec_cache.py
env_canada/ec_exc.py
env_canada/ec_historical.py
env_canada/ec_hydro.py
env_canada/ec_map.py
env_canada/ec_radar.py
env_canada/ec_weather.py
env_canada-0.12.4.dist-info/licenses/LICENSE
env_canada-0.12.4.dist-info/METADATA
env_canada-0.12.4.dist-info/WHEEL
env_canada-0.12.4.dist-info/top_level.txt
env_canada-0.12.4.dist-info/RECORD
