Metadata-Version: 2.4
Name: env_canada
Version: 0.12.4
Summary: A package to access meteorological data from Environment Canada
Author-email: Michael Davie <michael.davie@gmail.com>
Maintainer-email: Michael Davie <michael.davie@gmail.com>
License-Expression: MIT
Project-URL: Homepage, https://github.com/michaeldavie/env_canada
Project-URL: Documentation, https://github.com/michaeldavie/env_canada
Project-URL: Repository, https://github.com/michaeldavie/env_canada
Project-URL: Issues, https://github.com/michaeldavie/env_canada/issues
Project-URL: Changelog, https://github.com/michaeldavie/env_canada/blob/master/CHANGELOG.md
Classifier: Programming Language :: Python :: 3
Classifier: Operating System :: OS Independent
Requires-Python: >=3.11
License-File: LICENSE
Requires-Dist: aiohttp>=3.9.0
Requires-Dist: geopy>=2.3.0
Requires-Dist: lxml>=5.3.0
Requires-Dist: pandas>=2.2.3
Requires-Dist: Pillow>=10.0.1
Requires-Dist: python-dateutil>=2.9
Requires-Dist: voluptuous>=0.15.2
Dynamic: license-file
